Metadata-Version: 1.1
Name: sgdatadog
Version: 0.0.1
Summary: AI powered by SGDATADOG
Home-page: UNKNOWN
Author: Mr LIU
Author-email: l1813379886@gmail.com
License: MIT
Keywords: sgdatadog
Platform: UNKNOWN
Classifier: Development Status :: 5 - Production/Stable
Classifier: Intended Audience :: Education
Classifier: Operating System :: Microsoft :: Windows :: Windows 10
Classifier: License :: OSI Approved :: MIT License
Classifier: Programming Language :: Python :: 3
